{
	"SUBMISSION": {
	"ACCESSION_NUMBER": "string",
	"SUBMISSIONTYPE": "string",
	"CIK": "string"
	},
	"COVERPAGE": {
	"ACCESSION_NUMBER": "string",
	"ISAMENDMENT": "string",
	"AMENDMENTNO": "Int8",
	"AMENDMENTTYPE": "string",
	"CONFDENIEDEXPIRED": "string",
	"REASONFORNONCONFIDENTIALITY": "string",
	"FILINGMANAGER_NAME": "string",
	"FILINGMANAGER_STREET1": "string",
	"FILINGMANAGER_STREET2": "string",
	"FILINGMANAGER_CITY": "string",
	"FILINGMANAGER_STATEORCOUNTRY": "string",
	"FILINGMANAGER_ZIPCODE": "string",
	"REPORTTYPE": "string",
	"FORM13FFILENUMBER": "string",
	"PROVIDEINFOFORINSTRUCTION5": "string",
	"ADDITIONALINFORMATION": "string"
	},
	"OTHERMANAGER": {
	"ACCESSION_NUMBER": "string",
	"OTHERMANAGER_SK": "Int64",
	"CIK": "string",
	"FORM13FFILENUMBER": "string",
	"NAME": "string"
	},
	"SIGNATURE": {
	"ACCESSION_NUMBER": "string",
	"NAME": "string",
	"TITLE": "string",
	"PHONE": "string",
	"SIGNATURE": "string",
	"CITY": "string",
	"STATEORCOUNTRY": "string"
	},
	"SUMMARYPAGE": {
	"ACCESSION_NUMBER": "string",
	"OTHERINCLUDEDMANAGERSCOUNT": "Int8",
	"TABLEENTRYTOTAL": "float32",
	"TABLEVALUETOTAL": "float32",
	"ISCONFIDENTIALOMITTED": "string"
	},
	"OTHERMANAGER2": {
	"ACCESSION_NUMBER": "string",
	"OTHERMANAGER_SK": "Int64",
	"CIK": "string",
	"FORM13FFILENUMBER": "string",
	"NAME": "string"
	},
	"INFOTABLE": {
	"ACCESSION_NUMBER": "string",
	"INFOTABLE_SK": "Int64",
	"NAMEOFISSUER": "string",
	"TITLEOFCLASS": "string",
	"CUSIP": "string",
	"VALUE": "float32",
	"SSHPRNAMT": "string",
	"SSHPRNAMTTYPE": "string",
	"PUTCALL": "string",
	"INVESTMENTDISCRETION": "string",
	"OTHERMANAGER": "string",
	"VOTING_AUTH_SOLE": "string",
	"VOTING_AUTH_SHARED": "string",
	"VOTING_AUTH_NONE": "string"
	}
}
	
